odoo/addons/mgmtsystem_hazard_risk/README.rst
odoo/addons/mgmtsystem_hazard_risk/__init__.py
odoo/addons/mgmtsystem_hazard_risk/__manifest__.py
odoo/addons/mgmtsystem_hazard_risk/data/mgmtsystem_hazard_risk_computation.xml
odoo/addons/mgmtsystem_hazard_risk/data/mgmtsystem_hazard_risk_type.xml
odoo/addons/mgmtsystem_hazard_risk/i18n/de.po
odoo/addons/mgmtsystem_hazard_risk/i18n/es.po
odoo/addons/mgmtsystem_hazard_risk/i18n/fr.po
odoo/addons/mgmtsystem_hazard_risk/i18n/hr.po
odoo/addons/mgmtsystem_hazard_risk/i18n/id.po
odoo/addons/mgmtsystem_hazard_risk/i18n/it.po
odoo/addons/mgmtsystem_hazard_risk/i18n/mgmtsystem_hazard_risk.pot
odoo/addons/mgmtsystem_hazard_risk/i18n/nb.po
odoo/addons/mgmtsystem_hazard_risk/i18n/pt_BR.po
odoo/addons/mgmtsystem_hazard_risk/i18n/sl.po
odoo/addons/mgmtsystem_hazard_risk/i18n/vi.po
odoo/addons/mgmtsystem_hazard_risk/migrations/13.0.1.0.0/noupdate_changes.xml
odoo/addons/mgmtsystem_hazard_risk/migrations/13.0.1.0.0/post-migration.py
odoo/addons/mgmtsystem_hazard_risk/models/__init__.py
odoo/addons/mgmtsystem_hazard_risk/models/common.py
odoo/addons/mgmtsystem_hazard_risk/models/mgmtsystem_hazard.py
odoo/addons/mgmtsystem_hazard_risk/models/mgmtsystem_hazard_residual_risk.py
odoo/addons/mgmtsystem_hazard_risk/models/mgmtsystem_hazard_risk_computation.py
odoo/addons/mgmtsystem_hazard_risk/models/mgmtsystem_hazard_risk_type.py
odoo/addons/mgmtsystem_hazard_risk/models/res_company.py
odoo/addons/mgmtsystem_hazard_risk/models/res_config_settings.py
odoo/addons/mgmtsystem_hazard_risk/readme/CONFIGURE.rst
odoo/addons/mgmtsystem_hazard_risk/readme/CONTRIBUTORS.rst
odoo/addons/mgmtsystem_hazard_risk/readme/DESCRIPTION.rst
odoo/addons/mgmtsystem_hazard_risk/security/ir.model.access.csv
odoo/addons/mgmtsystem_hazard_risk/security/mgmtsystem_hazard_security.xml
odoo/addons/mgmtsystem_hazard_risk/static/description/icon.png
odoo/addons/mgmtsystem_hazard_risk/static/description/index.html
odoo/addons/mgmtsystem_hazard_risk/tests/__init__.py
odoo13_addon_mgmtsystem_hazard_risk-13.0.1.0.1.dev16.dist-info/METADATA
odoo13_addon_mgmtsystem_hazard_risk-13.0.1.0.1.dev16.dist-info/WHEEL
odoo13_addon_mgmtsystem_hazard_risk-13.0.1.0.1.dev16.dist-info/top_level.txt
odoo13_addon_mgmtsystem_hazard_risk-13.0.1.0.1.dev16.dist-info/RECORD
